animationer/__init__.py
animationer/__main__.py
animationer-1.0.4.dist-info/METADATA
animationer-1.0.4.dist-info/WHEEL
animationer-1.0.4.dist-info/top_level.txt
animationer-1.0.4.dist-info/RECORD
