Metadata-Version: 2.1
Name: animationer
Version: 1.0.4
Summary: A lightweight animation library for console applications. Made entirely in my free time.
Author: LeWolfYT
Author-email: ciblox3@gmail.com
License: MIT
